pyprofit.so
pyprofit.libs/libgslcblas-15b2d0fe.so.0.0.0
pyprofit.libs/libprofit-29312200.so
pyprofit.libs/libgomp-3300acd3.so.1.0.0
pyprofit.libs/libfftw3-c8dcb815.so.3.2.4
pyprofit.libs/libgsl-b885fd68.so.0.14.0
pyprofit-1.9.0.dist-info/RECORD
pyprofit-1.9.0.dist-info/WHEEL
pyprofit-1.9.0.dist-info/METADATA
pyprofit-1.9.0.dist-info/top_level.txt
pyprofit-1.9.0.dist-info/COPYING
